{"cameraMode":{"drawMode":0,"name":"Shaded","section":"Shading Mode"},"sceneLighting":true,"audioPlay":false,"sceneViewState":{"m_AlwaysRefresh":false,"showFog":true,"showSkybox":true,"showFlares":true,"showImageEffects":true,"showParticleSystems":true,"showVisualEffectGraphs":true,"m_FxEnabled":true},"in2DMode":false,"pivot":{"x":-31.627574920654298,"y":-5.029729843139648,"z":3.799546480178833},"rotation":{"x":-0.1237705647945404,"y":0.7119327783584595,"z":-0.1297740787267685,"w":-0.678959846496582},"size":24.83338737487793,"orthographic":false}